{
	"name": "Annabella",
	"type": "ITEM_TYPE_MATRIX",
	"description": "Gosip yang membosankan, ssh.",
	"icon": "icon_matrix_SSR21_512",
	"gachaIcon": "icon_matrix_SSR21_512",
	"rarity": "SSR",
	"set": [
		{
			"2": "Meningkatkan Final DMG sebesar **3%**/3.4%/3.8%/4.2% dan Crit Rate Final sebesar **2%**/2%/2.4%/2.4% selama **25** detik saat menghantam target dengan Senjata Flame. Maks **2** tumpuk. Saat efek ini didapatkan berulang-ulang, hanya efek dengan rating bintang tertinggi yang akan aktif.",
			"4": "Saat memakai 2 Senjata Flame atau lebih, mendapatkan efek Flowing Fire yang meningkatkan Final DMG sebesar **7%**/8%/9%/10% dan meningkatkan Crit DMG lagi sebesar **12%**/14%/16%/18% selama **25** detik setelah mendaratkan serangan Crit. Untuk setiap **3** Serangan Charged yang menghantam target, memulihkan **1** jatah menghindar. CD: **2** detik. Saat efek ini didapatkan berulang kali, hanya efek dengan rating bintang tertinggi yang akan aktif."
		}
	],
	"id": "matrix_SSR21_1"
}