{
	"name": "霜冻长枪",
	"description": "沃兰雪原居民常用的武器，根据地域特点增加了寒冰属性。平价而高效，广受欢迎。",
	"icon": "item_Weapon_R_Spear_Ice01",
	"gachaIcon": "Weapon_R_Spear_Ice01",
	"rarity": "R",
	"element": "Ice",
	"weaponType": "Spear",
	"wc": "DPS",
	"mats": {
		"Item_Mine_ice": 15,
		"Item_Mine_ice_02": 25,
		"Item_breakthrough_A2": 25,
		"Item_breakthrough_D2": 25,
		"Item_Mine_ice_03": 14,
		"Item_breakthrough_A3": 14,
		"Item_breakthrough_D3": 14,
		"Item_breakthrough_A1": 13,
		"Item_breakthrough_D1": 12
	},
	"advanceID": "spear_ice_r_star",
	"skills": {
		"normals": [
			{
				"name": "长枪普攻",
				"description": "在地面时，挥舞长枪可连续进行五次攻击。\r\n第一次攻击对目标造成**20.1%***攻击力+**121**点伤害，并小幅击退目标。\r\n第二次攻击对目标造成**18.5%***攻击力+**111**点伤害，并小幅击退目标。\r\n第三次攻击对目标造成**38.5%***攻击力+**231**点伤害，并小幅击退目标。\r\n第四次攻击对目标造成**59.2%***攻击力+**355**点伤害，并小幅击退目标。\r\n第五次攻击对目标造成**93.8%***攻击力+**563**点伤害，并大幅击退目标。",
				"icon": "skill_spear_melee",
				"id": "GA_FPlayerSpearMelee_Melee_R"
			},
			{
				"name": "飞击",
				"description": "当拓荒者滞空时，点击普攻可在空中连续进行四次攻击。\r\n第一次攻击对目标造成**22.3%***攻击力+**134**点伤害。\r\n第二次攻击对目标造成**18.8%***攻击力+**113**点伤害。\r\n第三次攻击对目标造成**37.1%***攻击力+**223**点伤害。\r\n第四次攻击对目标造成**89%***攻击力+**534**点伤害。",
				"icon": "skill_spear_air",
				"id": "GA_FPlayerSpearMelee_AirAttack_R"
			},
			{
				"name": "破击",
				"description": "滞空时长按普攻(存在敌方目标时点按），攀爬，反向跳攻击或使用喷气背包普攻，会触发破击。\r\n下落过程中，每次命中目标对目标造成**6.4%***攻击力+**38**点伤害；落地时对周围目标造成**39.3%***攻击力+**236**点伤害，并浮空目标。\r\n触发时离地距离越高，伤害越高，最高可达**600%**伤害。",
				"icon": "skill_spear_jump",
				"id": "GA_FPlayerSpearMelee_JumpAttack_R"
			},
			{
				"name": "乱枪狂舞",
				"description": "普攻第三下后，长按普攻可触发乱枪狂舞。\r\n命中目标会**强控浮空**目标造成**39.8%***攻击力+**239**点伤害；再次点击对浮空目标连续攻击，对单个目标最多可造成**79.5%***攻击力+**477**点伤害。",
				"icon": "skill_spear_branch",
				"id": "GA_FPlayerSpearMelee_Branch_R"
			},
			{
				"name": "偷袭",
				"description": "长枪刺出，对目标造成**256.5%***攻击力+**1539**点伤害。",
				"icon": "common_sneak",
				"id": "GA_FPlayerSpearMelee_Sneak_R"
			}
		],
		"dodge": [
			{
				"name": "飞踢",
				"description": "使用方向键加闪避按钮触发前闪避的短暂时间内，点击普攻，可触发飞踢。\r\n飞踢命中目标造成**58.2%***攻击力+**349**点伤害，大幅击退目标并对怪物造成**1**秒，对玩家造成**0.5**秒**强控眩晕**效果。",
				"icon": "skill_spear_frontattack",
				"id": "GA_FPlayerSpearEvade_FrontAttack_R"
			},
			{
				"name": "挑击",
				"description": "闪避之后的短暂时间内，点击普攻，可触发挑击。\r\n挥舞长枪砸地造成**强控浮空**效果，造成**42.8%***攻击力+**257**点伤害。",
				"icon": "skill_spear_backattck",
				"id": "GA_FPlayerSpearEvade_BackAttack_R"
			},
			{
				"name": "闪避",
				"description": "在被命中前闪避，可触发幻时，使一定范围内的目标动作速率变缓；闪避过程中，免疫硬直效果，持续**0.5**秒。",
				"icon": "common_evade",
				"id": "GA_FPlayerSpearEvade_Evade_R"
			}
		],
		"skill": [
			{
				"name": "逐月",
				"description": "旋风一般将目标**强控浮空**，并使拓荒者滞空，造成**103.1%***攻击力+**619**点伤害，冷却**25**秒。",
				"icon": "spear_skill1",
				"id": "GA_FPlayerSpearSkill_R"
			}
		],
		"discharge": [
			{
				"name": "长击飞挑",
				"description": "当**武器充能满**或触发**幻时**时，从其他武器切换到该武器时**清除自身负面状态**，抓取目标，并将目标多次甩动，造成**205.4%***攻击力+**1232**点伤害，最后一击附带**强控浮空**效果。",
				"icon": "skill_spear_changeskill",
				"id": "GA_FPlayerSpearChangeSkill_Success_R"
			}
		]
	},
	"stars": [
		{
			"stats": {
				"shatter": 6.9,
				"charge": 5.6
			},
			"need": "None"
		}
	],
	"id": "spear_ice"
}