{
  "dog" : {
    "name" : "DNT\n\n",
    "icon" : "None"
  },
  "Fish" : {
    "name" : "Fish",
    "icon" : "fish_1_d"
  },
  "Pet_Fish_007" : {
    "name" : "Blue Angelfish",
    "icon" : "Fish07"
  },
  "Pet_Fish_008" : {
    "name" : "Flashy Angelfish",
    "icon" : "Fish08"
  },
  "Pet_Fish_009" : {
    "name" : "Black Tigerfly Fish",
    "icon" : "Fish09"
  },
  "Pet_Fish_010" : {
    "name" : "Round sea bream",
    "icon" : "Fish10"
  },
  "Pet_Fish_011" : {
    "name" : "Blue Surgeonfish",
    "icon" : "Fish11"
  },
  "Pet_Fish_012" : {
    "name" : "Purple puffer",
    "icon" : "Fish12"
  },
  "Pet_Fish_013" : {
    "name" : "High-Back Fish",
    "icon" : "Fish13"
  },
  "Pet_Fish_014" : {
    "name" : "Green snapper",
    "icon" : "Fish14"
  },
  "Pet_Fish_015" : {
    "name" : "Scarlet Eye",
    "icon" : "Fish15"
  },
  "Pet_Fish_016" : {
    "name" : "Golden stripe puffer",
    "icon" : "Fish16"
  },
  "Pet_Fish_017" : {
    "name" : "Bell Fish",
    "icon" : "Fish17"
  },
  "Pet_Fish_018" : {
    "name" : "Tiger shrimp vegetables",
    "icon" : "Fish18"
  },
  "Pet_Fish_019" : {
    "name" : "Fantasy",
    "icon" : "Fish19"
  },
  "Pet_Fish_020" : {
    "name" : "Silver bone",
    "icon" : "Fish20"
  },
  "Pet_Fish_021" : {
    "name" : "Lemon yellow",
    "icon" : "Fish21"
  },
  "Pet_Fish_022" : {
    "name" : "Cloudy Angelfish",
    "icon" : "Fish22"
  },
  "Pet_Fish_023" : {
    "name" : "Red mane fish",
    "icon" : "Fish23"
  },
  "Pet_Fish_024" : {
    "name" : "Changing fish",
    "icon" : "Fish24"
  },
  "Pet_Fish_025" : {
    "name" : "Wingless",
    "icon" : "Fish25"
  },
  "Pet_Fish_026" : {
    "name" : "Sparky fish",
    "icon" : "Fish26"
  },
  "Pet_Fish_027" : {
    "name" : "Dark purple tiger shrimp",
    "icon" : "Fish27"
  },
  "Pet_Fish_028" : {
    "name" : "Midnight fish",
    "icon" : "Fish28"
  },
  "Pet_Fish_029" : {
    "name" : "Green-blue fish",
    "icon" : "Fish29"
  },
  "Pet_Fish_030" : {
    "name" : "Angry fish",
    "icon" : "Fish30"
  },
  "Pet_Fish_031" : {
    "name" : "Spiky sea bream",
    "icon" : "Fish31"
  },
  "Pet_Fish_032" : {
    "name" : "Red tail",
    "icon" : "Fish32"
  },
  "Pet_Cat_001" : {
    "name" : "Mittens",
    "icon" : "item_pet_cat2"
  },
  "Pet_Cat_002" : {
    "name" : "Ginger",
    "icon" : "item_pet_cat3"
  },
  "Pet_Cat_003" : {
    "name" : "Misty",
    "icon" : "item_pet_cat1"
  },
  "Pet_Cat_004" : {
    "name" : "Turty",
    "icon" : "item_pet_cat4"
  },
  "Pet_Dog_001" : {
    "name" : "Mars",
    "icon" : "item_pet_dog1"
  },
  "Pet_Dog_002" : {
    "name" : "Marvel",
    "icon" : "item_pet_dog2"
  },
  "Pet_Duck_001" : {
    "name" : "Chocolate",
    "icon" : "item_pet_duck"
  },
  "Pet_Rabbit_001" : {
    "name" : "Snowball",
    "icon" : "item_pet_rabbit"
  },
  "Pet_Fox_001" : {
    "name" : "Alabaster",
    "icon" : "item_pet_fox"
  },
  "Pet_Fish_007K" : {
    "name" : "Alpha Blue Angelfish",
    "icon" : "Fish07"
  },
  "Pet_Fish_008K" : {
    "name" : "Alpha Flashy Angelfish",
    "icon" : "Fish08"
  },
  "Pet_Fish_009K" : {
    "name" : "Alpha Black Tigerfly Fish",
    "icon" : "Fish09"
  },
  "Pet_Fish_010K" : {
    "name" : "Alpha Round Sea Bream",
    "icon" : "Fish10"
  },
  "Pet_Fish_011K" : {
    "name" : "Alpha Blue Surgeonfish",
    "icon" : "Fish11"
  },
  "Pet_Fish_012K" : {
    "name" : "Alpha Purple Puffer",
    "icon" : "Fish12"
  },
  "Pet_Fish_013K" : {
    "name" : "Alpha High-back Fish",
    "icon" : "Fish13"
  },
  "Pet_Fish_014K" : {
    "name" : "Alpha Green Snapper",
    "icon" : "Fish14"
  },
  "Pet_Fish_015K" : {
    "name" : "Alpha Scarlet Eye",
    "icon" : "Fish15"
  },
  "Pet_Fish_016K" : {
    "name" : "Alpha Golden Stripe Puffer",
    "icon" : "Fish16"
  },
  "Pet_Fish_017K" : {
    "name" : "Alpha Bell Fish",
    "icon" : "Fish17"
  },
  "Pet_Fish_018K" : {
    "name" : "Alpha Fruit Goby",
    "icon" : "Fish18"
  },
  "Pet_Fish_019K" : {
    "name" : "Alpha Fantasy Fish",
    "icon" : "Fish19"
  },
  "Pet_Fish_020K" : {
    "name" : "Alpha Silver Bone",
    "icon" : "Fish20"
  },
  "Pet_Fish_021K" : {
    "name" : "Alpha Lemon Yellow",
    "icon" : "Fish21"
  },
  "Pet_Fish_022K" : {
    "name" : "Alpha Cloudy Angelfish",
    "icon" : "Fish22"
  },
  "Pet_Fish_023K" : {
    "name" : "Alpha Red Mane Fish",
    "icon" : "Fish23"
  },
  "Pet_Fish_024K" : {
    "name" : "Alpha Changing Fish",
    "icon" : "Fish24"
  },
  "Pet_Fish_025K" : {
    "name" : "Alpha Wingless",
    "icon" : "Fish25"
  },
  "Pet_Fish_026K" : {
    "name" : "Alpha Sparky Fish",
    "icon" : "Fish26"
  },
  "Pet_Fish_027K" : {
    "name" : "Alpha Maroon Night Goby",
    "icon" : "Fish27"
  },
  "Pet_Fish_028K" : {
    "name" : "Alpha Midnight Fish",
    "icon" : "Fish28"
  },
  "Pet_Fish_029K" : {
    "name" : "Alpha Green-blue Fish",
    "icon" : "Fish29"
  },
  "Pet_Fish_030K" : {
    "name" : "Alpha Angry Fish",
    "icon" : "Fish30"
  },
  "Pet_Fish_031K" : {
    "name" : "Alpha Spiky Sea Bream",
    "icon" : "Fish31"
  },
  "Pet_Fish_032K" : {
    "name" : "Alpha Anchovy",
    "icon" : "Fish32"
  }
}