{
	"name": "Saki Fuwa",
	"type": "ITEM_TYPE_MATRIX",
	"description": "Eine fesselnde Aktion.",
	"icon": "icon_matrix_SSR17_512",
	"gachaIcon": "icon_matrix_SSR17_512",
	"rarity": "SSR",
	"set": [
		{
			"2": "Wenn „Frostresonanz“ ausgelöst wird: Alle **0**Sek. wird Gegnern in einem Umkreis von 10Metern Schaden in Höhe von **65%**/80%/95%/110% des Frost-ANG zugefügt und sie werden mit dem „Eisfrost“-Effekt belegt: Das Ziel wird **1**Sek. lang um -5% verlangsamt und nach dem Erreichen von 3Stapeln **3**Sek. lang eingefroren (Bosse können nicht eingefroren werden). Zudem wird der vom Ziel erlittene Frostschaden **5**Sek. lang um **5%** erhöht. Diese Matrix wird auch im Nebenhand-Slot aktiviert. Dabei ist aber nur das Set mit der höchsten Sternebewertung aktiv.",
			"4": "Greife das Ziel **10**-mal an und verursache eine {0 Sek. andauernde Blitzeinfrieren-Markierung. Blitzeinfrieren: Erhöht den Frostschaden, den das markierte Ziel erleidet, um **11%**/13%/15%/17%. Diese Matrix wird auch im Nebenhand-Slot aktiviert, aber nur das Set mit der höchsten Sternebewertung tritt in Kraft."
		}
	],
	"id": "matrix_SSR17_1"
}