{
  "Item_gift_1001": {
    "id": "Item_gift_1001",
    "name": "花束",
    "desc": "美しく包装された花束。プレゼントの定番だが、花粉症や植物嫌いの方には贈らないで。アーシャ地区の特産品なので、他の地区のアバターは興味がないかもしれない",
    "quality": "COMMON",
    "hobby_flag": [
      "everydayObjects",
      "Asshai"
    ],
    "value": 10,
    "assets": {
      "icon": "/Icon/ImitationGift/gift01.webp"
    }
  },
  "Item_gift_1002": {
    "id": "Item_gift_1002",
    "name": "ダンベル",
    "desc": "筋肉のパワー増強を目的としたトレーニング器具。一般的にはフィットネスの時に使用されるが、ごくまれに不思議な用途で使用される。アーシャ地区の特産品なので、他の地区のアバターは興味がないかもしれない",
    "quality": "COMMON",
    "hobby_flag": [
      "metal",
      "Asshai"
    ],
    "value": 10,
    "assets": {
      "icon": "/Icon/ImitationGift/gift02.webp"
    }
  },
  "Item_gift_1003": {
    "id": "Item_gift_1003",
    "name": "美しいフォトフレーム",
    "desc": "大切な記念写真を飾るフレームが壊れないように、特殊な構造で作られている。分解は至難の業であり、変に試さない方がいい。アーシャ地区の特産品なので、他の地区のアバターは興味がないかもしれない",
    "quality": "COMMON",
    "hobby_flag": [
      "decorate",
      "Asshai"
    ],
    "value": 10,
    "assets": {
      "icon": "/Icon/ImitationGift/gift03.webp"
    }
  },
  "Item_gift_1004": {
    "id": "Item_gift_1004",
    "name": "アイダ星のはがき",
    "desc": "アイダ星各地の様々な風景が楽しめるポストカード。オムニアムに汚染された劣悪な環境下でも、美しい景色は永遠に残しておく価値がある。アーシャ地区の特産品なので、他の地区のアバターは興味がないかもしれない",
    "quality": "COMMON",
    "hobby_flag": [
      "rarity",
      "Asshai"
    ],
    "value": 10,
    "assets": {
      "icon": "/Icon/ImitationGift/gift04.webp"
    }
  },
  "Item_gift_1005": {
    "id": "Item_gift_1005",
    "name": "カシミヤのマフラー",
    "desc": "このマフラーは以前はカシミヤで作られていたが、今はカシミヤ風の化学繊維が使われている。アーシャ地区の特産品なので、他の地区のアバターは興味がないかもしれない",
    "quality": "COMMON",
    "hobby_flag": [
      "everydayObjects",
      "Asshai"
    ],
    "value": 10,
    "assets": {
      "icon": "/Icon/ImitationGift/gift05.webp"
    }
  },
  "Item_gift_1006": {
    "id": "Item_gift_1006",
    "name": "特製トランプ",
    "desc": "このトランプの作成者は不明だが、ルールを読むとかなりおもしろい人物であることが分かる。アーシャ地区の特産品なので、他の地区のアバターは興味がないかもしれない",
    "quality": "COMMON",
    "hobby_flag": [
      "game",
      "Asshai"
    ],
    "value": 10,
    "assets": {
      "icon": "/Icon/ImitationGift/gift41.webp"
    }
  },
  "Item_gift_1007": {
    "id": "Item_gift_1007",
    "name": "ミニ盆栽",
    "desc": "鑑賞用のミニ植物。ただし本物ではなく、お世話いらずの人工観葉植物。アーシャ地区の特産品なので、他の地区のアバターは興味がないかもしれない",
    "quality": "COMMON",
    "hobby_flag": [
      "decorate",
      "Asshai"
    ],
    "value": 10,
    "assets": {
      "icon": "/Icon/ImitationGift/gift06.webp"
    }
  },
  "Item_gift_1008": {
    "id": "Item_gift_1008",
    "name": "レトロなハーモニカ",
    "desc": "美しい音色を奏でる楽器。入手が困難で、アイダ星でハーモニカを吹けるのは相当な音楽マニアくらいだ。アーシャ地区の特産品なので、他の地区のアバターは興味がないかもしれない",
    "quality": "COMMON",
    "hobby_flag": [
      "rarity",
      "Asshai"
    ],
    "value": 10,
    "assets": {
      "icon": "/Icon/ImitationGift/gift07.webp"
    }
  },
  "Item_gift_1009": {
    "id": "Item_gift_1009",
    "name": "風車",
    "desc": "平凡極まりないおもちゃ。でもこういう普通なおもちゃほど、使いやすくて楽しめる。アーシャ地区の特産品なので、他の地区のアバターは興味がないかもしれない",
    "quality": "COMMON",
    "hobby_flag": [
      "toy",
      "Asshai"
    ],
    "value": 10,
    "assets": {
      "icon": "/Icon/ImitationGift/gift08.webp"
    }
  },
  "Item_gift_1010": {
    "id": "Item_gift_1010",
    "name": "おやつセット",
    "desc": "アストラ島のサミーが最初に売り出したおやつセット。魅力的なお菓子がぎっしり入っており、カジュアルな贈り物として各界から支持を集めている。アーシャ地区の特産品なので、他の地区のアバターは興味がないかもしれない",
    "quality": "COMMON",
    "hobby_flag": [
      "restrictedGoods",
      "Asshai"
    ],
    "value": 10,
    "assets": {
      "icon": "/Icon/ImitationGift/gift09.webp"
    }
  },
  "Item_gift_1011": {
    "id": "Item_gift_1011",
    "name": "ツキメソウのオブジェ",
    "desc": "ツキメソウをモデルに作られたオブジェ。生態系改良プロジェクトが進んでしばらくした後、ヴェラの砂漠で初めてツキメソウのつぼみが発見された",
    "quality": "COMMON",
    "hobby_flag": [
      "collection",
      "Vera"
    ],
    "value": 10,
    "assets": {
      "icon": "/Icon/ImitationGift/UI_jingdu_icon_hua_256.webp"
    }
  },
  "Item_gift_2001": {
    "id": "Item_gift_2001",
    "name": "役立つ工具セット",
    "desc": "そのまま使えて、部品として他の機械に差し込むこともできるフレキシブルな工具セット。実用性が高く、技術スタッフにも大好評。アーシャ地区の特産品なので、他の地区のアバターは興味がないかもしれない",
    "quality": "RARE",
    "hobby_flag": [
      "metal",
      "Asshai"
    ],
    "value": 20,
    "assets": {
      "icon": "/Icon/ImitationGift/gift10.webp"
    }
  },
  "Item_gift_2002": {
    "id": "Item_gift_2002",
    "name": "チェス",
    "desc": "2人対戦型のボードゲームだが、時々人生を賭けてしまう人もいる。アーシャ地区の特産品なので、他の地区のアバターは興味がないかもしれない",
    "quality": "RARE",
    "hobby_flag": [
      "game",
      "Asshai"
    ],
    "value": 20,
    "assets": {
      "icon": "/Icon/ImitationGift/gift11.webp"
    }
  },
  "Item_gift_2003": {
    "id": "Item_gift_2003",
    "name": "ぬいぐるみ",
    "desc": "子どもたちに大人気な柔らかいタイプのおもちゃ。かわいくて、暖かなお日様の匂いがする。アーシャ地区の特産品なので、他の地区のアバターは興味がないかもしれない",
    "quality": "RARE",
    "hobby_flag": [
      "toy",
      "Asshai"
    ],
    "value": 20,
    "assets": {
      "icon": "/Icon/ImitationGift/gift12.webp"
    }
  },
  "Item_gift_2004": {
    "id": "Item_gift_2004",
    "name": "オーダースーツ",
    "desc": "オーダーメイドスーツ。既製品にはない風格があり、装飾もついている。ショーが大好きな人にウケそう。アーシャ地区の特産品なので、他の地区のアバターは興味がないかもしれない",
    "quality": "RARE",
    "hobby_flag": [
      "everydayObjects",
      "Asshai"
    ],
    "value": 20,
    "assets": {
      "icon": "/Icon/ImitationGift/gift13.webp"
    }
  },
  "Item_gift_2005": {
    "id": "Item_gift_2005",
    "name": "ビタミン補給パック",
    "desc": "生命維持に不可欠な栄養補給パック。徹夜で働く人、ゲームに夢中になってエネルギー補給を忘れがちな人には欠かせない食品。アーシャ地区の特産品なので、他の地区のアバターは興味がないかもしれない",
    "quality": "RARE",
    "hobby_flag": [
      "everydayObjects",
      "Asshai"
    ],
    "value": 20,
    "assets": {
      "icon": "/Icon/ImitationGift/gift14.webp"
    }
  },
  "Item_gift_2006": {
    "id": "Item_gift_2006",
    "name": "宝石のネックレス",
    "desc": "この宝石って高いんだろうなという余計な感慨はさておき、早くこの貴重なアイテムを大事にしまうことだ!!アーシャ地区の特産品なので、他の地区のアバターは興味がないかもしれない",
    "quality": "RARE",
    "hobby_flag": [
      "collection",
      "Asshai"
    ],
    "value": 20,
    "assets": {
      "icon": "/Icon/ImitationGift/gift15.webp"
    }
  },
  "Item_gift_2007": {
    "id": "Item_gift_2007",
    "name": "ネコ型抱き枕",
    "desc": "ネコの形をした抱き枕。ぎゅっと抱きしめていると、気分がほんわかして癒される。アーシャ地区の特産品なので、他の地区のアバターは興味がないかもしれない",
    "quality": "RARE",
    "hobby_flag": [
      "toy",
      "Asshai"
    ],
    "value": 20,
    "assets": {
      "icon": "/Icon/ImitationGift/gift16.webp"
    }
  },
  "Item_gift_2008": {
    "id": "Item_gift_2008",
    "name": "塗り絵",
    "desc": "塗り絵店の店主が、色鉛筆で全ページを塗り終えたら新しいものと交換してくれると言った。アーシャ地区の特産品なので、他の地区のアバターは興味がないかもしれない",
    "quality": "RARE",
    "hobby_flag": [
      "game",
      "Asshai"
    ],
    "value": 20,
    "assets": {
      "icon": "/Icon/ImitationGift/gift17.webp"
    }
  },
  "Item_gift_2009": {
    "id": "Item_gift_2009",
    "name": "隕石ボトル",
    "desc": "宇宙の流星の燃え残りのような隕石が入った透明な瓶。石鉄混合の物質で、淡い光を放っている。アーシャ地区の特産品なので、他の地区のアバターは興味がないかもしれない",
    "quality": "RARE",
    "hobby_flag": [
      "rarity",
      "Asshai"
    ],
    "value": 20,
    "assets": {
      "icon": "/Icon/ImitationGift/gift18.webp"
    }
  },
  "Item_gift_2010": {
    "id": "Item_gift_2010",
    "name": "Perfume bottle",
    "desc": "豪華なデザインの上品なガラス瓶。中の液体が強い香りを放っている。アーシャ地区の特産品なので、他の地区のアバターは興味がないかもしれない",
    "quality": "RARE",
    "hobby_flag": [
      "everydayObjects",
      "Asshai"
    ],
    "value": 20,
    "assets": {
      "icon": "/Icon/ImitationGift/gift19.webp"
    }
  },
  "Item_gift_2011": {
    "id": "Item_gift_2011",
    "name": "タルタロスのオブジェ",
    "desc": "動物型のオブジェ。タルタロスをモデルにしているそうだ。アーシャ地区の特産品なので、他の地区のアバターは興味がないかもしれない",
    "quality": "RARE",
    "hobby_flag": [
      "decorate",
      "Asshai"
    ],
    "value": 20,
    "assets": {
      "icon": "/Icon/ImitationGift/gift20.webp"
    }
  },
  "Item_gift_2012": {
    "id": "Item_gift_2012",
    "name": "カカの新型オブジェ",
    "desc": "旧型カカの生産終了決定時に大量の苦情が届いたため、製造業者による再三の検討の末、リニューアル版が発売された。アーシャ地区の特産品なので、他の地区のアバターは興味がないかもしれない",
    "quality": "RARE",
    "hobby_flag": [
      "decorate",
      "Asshai"
    ],
    "value": 20,
    "assets": {
      "icon": "/Icon/ImitationGift/gift21.webp"
    }
  },
  "Item_gift_2013": {
    "id": "Item_gift_2013",
    "name": "クレイジー・ダイモンのフィギュア",
    "desc": "いつの間に大流行中のクレイジー・ダイモンのフィギュア。みんな1つは持っている。アーシャ地区の特産品なので、他の地区のアバターは興味がないかもしれない",
    "quality": "RARE",
    "hobby_flag": [
      "garageKit",
      "Asshai"
    ],
    "value": 20,
    "assets": {
      "icon": "/Icon/ImitationGift/gift22.webp"
    }
  },
  "Item_gift_2014": {
    "id": "Item_gift_2014",
    "name": "月うさぎの組み立ておもちゃ",
    "desc": "組み立て型のおもちゃ、月うさぎをイメージしたデザイン。アーシャ地区の特産品なので、他の地区のアバターは興味がないかもしれない",
    "quality": "RARE",
    "hobby_flag": [
      "toy",
      "Asshai"
    ],
    "value": 20,
    "assets": {
      "icon": "/Icon/ImitationGift/gift23.webp"
    }
  },
  "Item_gift_2015": {
    "id": "Item_gift_2015",
    "name": "レイキのフィギュア",
    "desc": "AIサーバントのレイキがモデルのフィギュア。アーシャ地区の特産品なので、他の地区のアバターは興味がないかもしれない",
    "quality": "RARE",
    "hobby_flag": [
      "garageKit",
      "Asshai"
    ],
    "value": 20,
    "assets": {
      "icon": "/Icon/ImitationGift/gift24.webp"
    }
  },
  "Item_gift_2016": {
    "id": "Item_gift_2016",
    "name": "ミラポリスブロック",
    "desc": "ミラポリスのミニモデルで、高い製作技術を要する",
    "quality": "RARE",
    "hobby_flag": [
      "metal",
      "Vera"
    ],
    "value": 20,
    "assets": {
      "icon": "/Icon/ImitationGift/UI_jingdu_icon_jimu_256.webp"
    }
  },
  "Item_gift_2017": {
    "id": "Item_gift_2017",
    "name": "ウサギの抱き枕",
    "desc": "ウサギの形をした抱き枕。ぎゅっと抱きしめていると、気分が和らいで癒される",
    "quality": "RARE",
    "hobby_flag": [
      "toy",
      "Vera"
    ],
    "value": 20,
    "assets": {
      "icon": "/Icon/ImitationGift/UI_jingdu_icon_tuzi_256.webp"
    }
  },
  "Item_gift_2018": {
    "id": "Item_gift_2018",
    "name": "墨汁壺",
    "desc": "墨汁は飲んじゃだめですよ!",
    "quality": "RARE",
    "hobby_flag": [
      "everydayObjects",
      "Jiuyu"
    ],
    "value": 20,
    "assets": {
      "icon": "/Icon/ImitationGift/gift50.webp"
    }
  },
  "Item_gift_2019": {
    "id": "Item_gift_2019",
    "name": "小さな桃木剣",
    "desc": "伝統技法で彫られた精巧な装飾品。収集家にも人気",
    "quality": "RARE",
    "hobby_flag": [
      "decorate",
      "Jiuyu"
    ],
    "value": 20,
    "assets": {
      "icon": "/Icon/ImitationGift/gift51.webp"
    }
  },
  "Item_gift_2020": {
    "id": "Item_gift_2020",
    "name": "炎陽のマフラー",
    "desc": "寒い冬に暖かさをもたらしてくれる、上質なマフラー",
    "quality": "RARE",
    "hobby_flag": [
      "everydayObjects",
      "Jiuyu"
    ],
    "value": 20,
    "assets": {
      "icon": "/Icon/ImitationGift/gift2020.webp"
    }
  },
  "Item_gift_3001": {
    "id": "Item_gift_3001",
    "name": "新型ゲーム機",
    "desc": "最新の先端ゲーム機。あるパソコンの天才が製作に携わったためにコストが高騰し、ひとまず限定販売されることになった。アーシャ地区の特産品なので、他の地区のアバターは興味がないかもしれない",
    "quality": "EPIC",
    "hobby_flag": [
      "restrictedGoods",
      "game",
      "Asshai"
    ],
    "value": 40,
    "assets": {
      "icon": "/Icon/ImitationGift/gift25.webp"
    }
  },
  "Item_gift_3002": {
    "id": "Item_gift_3002",
    "name": "雪の水晶玉",
    "desc": "フォラント雪原産の球状結晶。雪の季節になると球内に純白の雪が舞う。今ではインテリア用に生産されている。アーシャ地区の特産品なので、他の地区のアバターは興味がないかもしれない",
    "quality": "EPIC",
    "hobby_flag": [
      "rarity",
      "decorate",
      "Asshai"
    ],
    "value": 40,
    "assets": {
      "icon": "/Icon/ImitationGift/gift26.webp"
    }
  },
  "Item_gift_3003": {
    "id": "Item_gift_3003",
    "name": "機械式オルゴール",
    "desc": "金属製のオルゴール。以前の持ち主が使い方を間違えたせいか、美しい旋律は次の持ち主に渡る前に完全に封印されている。アーシャ地区の特産品なので、他の地区のアバターは興味がないかもしれない",
    "quality": "EPIC",
    "hobby_flag": [
      "metal",
      "game",
      "Asshai"
    ],
    "value": 40,
    "assets": {
      "icon": "/Icon/ImitationGift/gift27.webp"
    }
  },
  "Item_gift_3004": {
    "id": "Item_gift_3004",
    "name": "銀食器セット",
    "desc": "豪華な銀食器フルセット。前の所有者である一流シェフは、誰にもこの貴重な食器を触らせなかったそうだ。アーシャ地区の特産品なので、他の地区のアバターは興味がないかもしれない",
    "quality": "EPIC",
    "hobby_flag": [
      "metal",
      "collection",
      "Asshai"
    ],
    "value": 40,
    "assets": {
      "icon": "/Icon/ImitationGift/gift28.webp"
    }
  },
  "Item_gift_3005": {
    "id": "Item_gift_3005",
    "name": "『漫画アイダ星』",
    "desc": "主人公「ティト」のアイダ星冒険を描いた月刊ファンタジー漫画。大人気で販売数が限定されているため、争奪戦が毎月繰り広げられている。アーシャ地区の特産品なので、他の地区のアバターは興味がないかもしれない",
    "quality": "EPIC",
    "hobby_flag": [
      "restrictedGoods",
      "everydayObjects",
      "Asshai"
    ],
    "value": 40,
    "assets": {
      "icon": "/Icon/ImitationGift/gift29.webp"
    }
  },
  "Item_gift_3006": {
    "id": "Item_gift_3006",
    "name": "ベンジスの特産品",
    "desc": "ベンジスの特産品を集めたギフトパック。箱ごとに商品の組み合わせが違うのも、ベンジスらしいところだ。当然ながら、中身は受け取った人だけのお楽しみ。アーシャ地区の特産品なので、他の地区のアバターは興味がないかもしれない",
    "quality": "EPIC",
    "hobby_flag": [
      "metal",
      "toy",
      "Asshai"
    ],
    "value": 40,
    "assets": {
      "icon": "/Icon/ImitationGift/gift30.webp"
    }
  },
  "Item_gift_3007": {
    "id": "Item_gift_3007",
    "name": "ハガードの立体パズル",
    "desc": "ハガードで一世を風靡したパズル。斬新なデザインや遊び方など、楽しい要素満載。アーシャ地区の特産品なので、他の地区のアバターは興味がないかもしれない",
    "quality": "EPIC",
    "hobby_flag": [
      "rarity",
      "game",
      "Asshai"
    ],
    "value": 40,
    "assets": {
      "icon": "/Icon/ImitationGift/gift31.webp"
    }
  },
  "Item_gift_3008": {
    "id": "Item_gift_3008",
    "name": "フォラントの化石",
    "desc": "時の回廊に冷凍保存された古生物が、長い時を経てフォラント雪原で発見された。収集価値のある超レアなアイテム。アーシャ地区の特産品なので、他の地区のアバターは興味がないかもしれない",
    "quality": "EPIC",
    "hobby_flag": [
      "rarity",
      "collection",
      "Asshai"
    ],
    "value": 40,
    "assets": {
      "icon": "/Icon/ImitationGift/gift32.webp"
    }
  },
  "Item_gift_3009": {
    "id": "Item_gift_3009",
    "name": "キリオン記念硬貨",
    "desc": "キリオン製の数量限定記念コイン。表にキリオン鉱山の社長の顔、裏にキリオンを表す「K」の文字が彫られている。7枚くらい集めると有給休暇がもらえるはず、多分...。アーシャ地区の特産品なので、他の地区のアバターは興味がないかもしれない",
    "quality": "EPIC",
    "hobby_flag": [
      "restrictedGoods",
      "collection",
      "Asshai"
    ],
    "value": 40,
    "assets": {
      "icon": "/Icon/ImitationGift/gift33.webp"
    }
  },
  "Item_gift_3010": {
    "id": "Item_gift_3010",
    "name": "ティトの数量限定フィギュア",
    "desc": "ラッピングされた限定フィギュア。『漫画アイダ星』の関連グッズ。アーシャ地区の特産品なので、他の地区のアバターは興味がないかもしれない",
    "quality": "EPIC",
    "hobby_flag": [
      "restrictedGoods",
      "garageKit",
      "Asshai"
    ],
    "value": 40,
    "assets": {
      "icon": "/Icon/ImitationGift/gift34.webp"
    }
  },
  "Item_gift_3011": {
    "id": "Item_gift_3011",
    "name": "フクちゃんの金属フィギュア",
    "desc": "モデルのフクちゃんの姿を忠実に再現するため、金属で製作された。アーシャ地区の特産品なので、他の地区のアバターは興味がないかもしれない",
    "quality": "EPIC",
    "hobby_flag": [
      "metal",
      "garageKit",
      "Asshai"
    ],
    "value": 40,
    "assets": {
      "icon": "/Icon/ImitationGift/gift35.webp"
    }
  },
  "Item_gift_3012": {
    "id": "Item_gift_3012",
    "name": "スマート人形",
    "desc": "スマートをモデルに制作されたおもちゃ。頭部のフェイクグリーンが本物の観葉植物に変更されたことで、収集価値が大いに高まった。アーシャ地区の特産品なので、他の地区のアバターは興味がないかもしれない",
    "quality": "EPIC",
    "hobby_flag": [
      "collection",
      "toy",
      "Asshai"
    ],
    "value": 40,
    "assets": {
      "icon": "/Icon/ImitationGift/gift36.webp"
    }
  },
  "Item_gift_3013": {
    "id": "Item_gift_3013",
    "name": "限定版ピーナッツ",
    "desc": "データ保存と音声認識機能付きの超レアフィギュア。ネコ型のピーナッツをモデルにしていて、ネコ好きにも大人気。アーシャ地区の特産品なので、他の地区のアバターは興味がないかもしれない",
    "quality": "EPIC",
    "hobby_flag": [
      "restrictedGoods",
      "decorate",
      "Asshai"
    ],
    "value": 40,
    "assets": {
      "icon": "/Icon/ImitationGift/gift37.webp"
    }
  },
  "Item_gift_3014": {
    "id": "Item_gift_3014",
    "name": "虚無の天使のフィギュア",
    "desc": "虚無の天使がモデルになっている真っ白なフィギュア。こまめなお手入れが必要。アーシャ地区の特産品なので、他の地区のアバターは興味がないかもしれない",
    "quality": "EPIC",
    "hobby_flag": [
      "rarity",
      "garageKit",
      "Asshai"
    ],
    "value": 40,
    "assets": {
      "icon": "/Icon/ImitationGift/gift40.webp"
    }
  },
  "Item_gift_3015": {
    "id": "Item_gift_3015",
    "name": "アンジェラのオブジェ",
    "desc": "AIサーバント・アンジェラのミニオブジェ。背中のピンク色のかわいい羽根も再現されている。アーシャ地区の特産品なので、他の地区のアバターは興味がないかもしれない",
    "quality": "EPIC",
    "hobby_flag": [
      "everydayObjects",
      "decorate",
      "Asshai"
    ],
    "value": 40,
    "assets": {
      "icon": "/Icon/ImitationGift/gift39.webp"
    }
  },
  "Item_gift_3016": {
    "id": "Item_gift_3016",
    "name": "アルティメット戦士タタ",
    "desc": "アルティメット戦士大戦シリーズ誕生40周年記念作品作品、アルティメット戦士大戦40thがリリース。今買うと強力なSSR限定キャラ「タタ」のグッズが付いてくる",
    "quality": "EPIC",
    "hobby_flag": [
      "toy",
      "decorate",
      "Vera"
    ],
    "value": 40,
    "assets": {
      "icon": "/Icon/ImitationGift/UI_jingdu_icon_jiujie_128.webp"
    }
  },
  "Item_gift_3017": {
    "id": "Item_gift_3017",
    "name": "学園アイドル・ヤヤ",
    "desc": "ミラポリスで売上No.1のフィギュア。どこか見覚えがある...ミラポリスで人気の高い某行政官をモデルにしているらしいが、フィギュア作者は否定している",
    "quality": "EPIC",
    "hobby_flag": [
      "collection",
      "garageKit",
      "Vera"
    ],
    "value": 40,
    "assets": {
      "icon": "/Icon/ImitationGift/UI_jingdu_icon_xiaoyeye_256.webp"
    }
  },
  "Item_gift_3018": {
    "id": "Item_gift_3018",
    "name": "デスメタル",
    "desc": "喉の奥から絞り出す叫び、魂を突き刺す衝撃派。それは音楽の殿堂への誘い",
    "quality": "EPIC",
    "hobby_flag": [
      "collection",
      "restrictedGoods",
      "Vera"
    ],
    "value": 40,
    "assets": {
      "icon": "/Icon/ImitationGift/gift47.webp"
    }
  },
  "Item_gift_3019": {
    "id": "Item_gift_3019",
    "name": "積木くずし",
    "desc": "パーティーの必需品。賢い仲間たちとの駆け引きは最高の喜び",
    "quality": "EPIC",
    "hobby_flag": [
      "game",
      "toy",
      "Vera"
    ],
    "value": 40,
    "assets": {
      "icon": "/Icon/ImitationGift/gift48.webp"
    }
  },
  "Item_gift_3020": {
    "id": "Item_gift_3020",
    "name": "ミラポリス観光ガイド",
    "desc": "観光客向けのミラポリス電子観光ガイド。制作時には実用を想定していなかった",
    "quality": "EPIC",
    "hobby_flag": [
      "rarity",
      "everydayObjects",
      "Vera"
    ],
    "value": 40,
    "assets": {
      "icon": "/Icon/ImitationGift/gift49.webp"
    }
  },
  "Item_gift_3021": {
    "id": "Item_gift_3021",
    "name": "九連環",
    "desc": "複雑な知恵の輪。解けなくても...叩き壊しちゃダメ!",
    "quality": "EPIC",
    "hobby_flag": [
      "game",
      "metal",
      "Jiuyu"
    ],
    "value": 40,
    "assets": {
      "icon": "/Icon/ImitationGift/gift52.webp"
    }
  },
  "Item_gift_3022": {
    "id": "Item_gift_3022",
    "name": "熊猫のぬいぐるみ",
    "desc": "斬新なデザインのパンダのぬいぐるみ。観文閣が売り出した秘密のマスコットだとか",
    "quality": "EPIC",
    "hobby_flag": [
      "toy",
      "garageKit",
      "Jiuyu"
    ],
    "value": 40,
    "assets": {
      "icon": "/Icon/ImitationGift/gift53.webp"
    }
  },
  "Item_gift_3023": {
    "id": "Item_gift_3023",
    "name": "『剣神十六伝』",
    "desc": "九域で人気の武侠小説。小説家・心剣の作。剣で各地を旅し、剣で天下を正す",
    "quality": "EPIC",
    "hobby_flag": [
      "collection",
      "restrictedGoods",
      "Jiuyu"
    ],
    "value": 40,
    "assets": {
      "icon": "/Icon/ImitationGift/gift54.webp"
    }
  },
  "Item_gift_3024": {
    "id": "Item_gift_3024",
    "name": "『如去神拳』",
    "desc": "少年よ、あなたには素晴らしい武術の素質がある。将来、九域の正義と平和を守る重大な使命をあなたに託します!ここに『如去神拳』という本があります。如去神拳とは目には見えない拳のことで...",
    "quality": "EPIC",
    "hobby_flag": [
      "collection",
      "rarity",
      "Jiuyu"
    ],
    "value": 40,
    "assets": {
      "icon": "/Icon/ImitationGift/gift55.webp"
    }
  },
  "Item_gift_3025": {
    "id": "Item_gift_3025",
    "name": "沈香扇",
    "desc": "香りを帯びた爽やかな涼風が楽しめる",
    "quality": "EPIC",
    "hobby_flag": [
      "everydayObjects",
      "decorate",
      "Jiuyu"
    ],
    "value": 40,
    "assets": {
      "icon": "/Icon/ImitationGift/gift56.webp"
    }
  },
  "Item_gift_3026": {
    "id": "Item_gift_3026",
    "name": "水墨ペン",
    "desc": "寒さが厳しい環境でもインクが固まらないよう、特殊な技術で作られたペン",
    "quality": "EPIC",
    "hobby_flag": [
      "restrictedGoods",
      "collection",
      "Jiuyu"
    ],
    "value": 40,
    "assets": {
      "icon": "/Icon/ImitationGift/gift3026.webp"
    }
  },
  "Item_gift_3027": {
    "id": "Item_gift_3027",
    "name": "毛皮の毛布",
    "desc": "希少な猛獣の毛皮で作られた毛布。シルクのように手触りが良く、防寒性が高い",
    "quality": "EPIC",
    "hobby_flag": [
      "collection",
      "rarity",
      "Jiuyu"
    ],
    "value": 40,
    "assets": {
      "icon": "/Icon/ImitationGift/gift3027.webp"
    }
  },
  "Item_gift_3028": {
    "id": "Item_gift_3028",
    "name": "白虎の氷像",
    "desc": "丁寧に彫刻され、磨き上げられた白虎の氷像。特殊な加工によって氷が溶ける心配がないため、贈り物に最適",
    "quality": "EPIC",
    "hobby_flag": [
      "collection",
      "decorate",
      "Jiuyu"
    ],
    "value": 40,
    "assets": {
      "icon": "/Icon/ImitationGift/gift3028.webp"
    }
  },
  "Item_gift_T101008": {
    "id": "Item_gift_T101008",
    "name": "脚本家の自己修養",
    "desc": "脚本家が日々のよしなしごとを綴ったエッセイ。催眠効果は抜群、寝る前の読書にもぴったりだ",
    "quality": "EPIC",
    "hobby_flag": [
      "everydayObjects",
      "restrictedGoods",
      "Vera"
    ],
    "value": 40,
    "assets": {
      "icon": "/Icon/ImitationGift/gift41.webp"
    }
  },
  "Item_gift_T101010": {
    "id": "Item_gift_T101010",
    "name": "保安部の訓練日誌",
    "desc": "保安部特殊部隊隊員の訓練計画か書かれた冊子。保安部のベテラン隊員が訓練方法を記しており、新人隊員にとってはかなり勉強になる",
    "quality": "EPIC",
    "hobby_flag": [
      "collection",
      "restrictedGoods",
      "Vera"
    ],
    "value": 40,
    "assets": {
      "icon": "/Icon/ImitationGift/gift41.webp"
    }
  },
  "Item_gift_T101011": {
    "id": "Item_gift_T101011",
    "name": "サイン入り絵ハガキ",
    "desc": "フェンリルの直筆サイン入り絵ハガキ",
    "quality": "EPIC",
    "hobby_flag": [
      "collection",
      "rarity",
      "Vera"
    ],
    "value": 40,
    "assets": {
      "icon": "/Icon/ImitationGift/gift04.webp"
    }
  },
  "Item_gift_T101015": {
    "id": "Item_gift_T101015",
    "name": "有名ライダーのサイン",
    "desc": "有名ライダーのサイン入り絵ハガキ",
    "quality": "EPIC",
    "hobby_flag": [
      "collection",
      "rarity",
      "Vera"
    ],
    "value": 40,
    "assets": {
      "icon": "/Icon/ImitationGift/gift04.webp"
    }
  },
  "Item_gift_T101037": {
    "id": "Item_gift_T101037",
    "name": "ウーミィのトランプ",
    "desc": "ウーミィのマジックアイテム。特に変わったところはないようだが...彼女に渡せば、ちょっとしたトリックを教えてくれるかも",
    "quality": "EPIC",
    "hobby_flag": [
      "game",
      "Vera"
    ],
    "value": 40,
    "assets": {
      "icon": "/Icon/ImitationGift/gift04.webp"
    }
  },
  "Item_gift_4021": {
    "id": "Item_gift_4021",
    "name": "金塊",
    "desc": "素朴で飾り気のない金の延べ棒。科学技術がこれほど進歩した現代においても、その魅力は変わらない",
    "quality": "EPIC",
    "hobby_flag": [
      "Genet",
      "metal",
      "collection",
      "rarity"
    ],
    "value": 40,
    "assets": {
      "icon": "/Icon/ImitationGift/gift4021.webp"
    }
  },
  "Item_gift_4001": {
    "id": "Item_gift_4001",
    "name": "素朴なレコード",
    "desc": "驚異的なセールスを記録したこのアルバムには、地元のポップソングが数多く収録され、多くの若者たちに親しまれている。芸術には上下関係があるなど、一体誰が言ったのだろうか?",
    "quality": "RARE",
    "hobby_flag": [
      "Genet",
      "collection",
      "everydayObjects"
    ],
    "value": 40,
    "assets": {
      "icon": "/Icon/ImitationGift/gift4001.webp"
    }
  },
  "Item_gift_4022": {
    "id": "Item_gift_4022",
    "name": "水族館のオーナメント",
    "desc": "美しい水晶球の中には光り輝く水生生物たちの模造品が入っており、振るとゆらゆらと泳ぎだす。女の子に大人気",
    "quality": "EPIC",
    "hobby_flag": [
      "Genet",
      "collection",
      "decorate"
    ],
    "value": 40,
    "assets": {
      "icon": "/Icon/ImitationGift/gift4022.webp"
    }
  },
  "Item_gift_4002": {
    "id": "Item_gift_4002",
    "name": "イルカのキーホルダー",
    "desc": "イルカの形をしたキーホルダー。丸みを帯びた可愛らしいデザインが一部の人々に愛されている",
    "quality": "RARE",
    "hobby_flag": [
      "Genet",
      "toy",
      "everydayObjects"
    ],
    "value": 40,
    "assets": {
      "icon": "/Icon/ImitationGift/gift4002.webp"
    }
  },
  "Item_gift_4023": {
    "id": "Item_gift_4023",
    "name": "雪華晶石",
    "desc": "希少な天然水晶に繊細な彫刻が施された芸術品。太陽光の下では透明に、水中ではわずかに青みを帯びる唯一無二の傑作である",
    "quality": "EPIC",
    "hobby_flag": [
      "Genet",
      "collection",
      "decorate"
    ],
    "value": 40,
    "assets": {
      "icon": "/Icon/ImitationGift/gift4023.webp"
    }
  },
  "Item_gift_4003": {
    "id": "Item_gift_4003",
    "name": "水晶の原石",
    "desc": "天然の水晶の原石。珍しい紫色をしており、加工前からその価値の高さがうかがえる",
    "quality": "RARE",
    "hobby_flag": [
      "Genet",
      "collection",
      "rarity"
    ],
    "value": 40,
    "assets": {
      "icon": "/Icon/ImitationGift/gift4003.webp"
    }
  },
  "Item_gift_4024": {
    "id": "Item_gift_4024",
    "name": "黒魔術師",
    "desc": "ゲームに登場する黒魔術師のカスタムフィギュア。全身が黒いローブに包まれており、ミステリアスかつ不気味な雰囲気を醸し出している",
    "quality": "EPIC",
    "hobby_flag": [
      "Genet",
      "game",
      "garageKit",
      "toy"
    ],
    "value": 40,
    "assets": {
      "icon": "/Icon/ImitationGift/gift4024.webp"
    }
  },
  "Item_gift_4004": {
    "id": "Item_gift_4004",
    "name": "20面ダイス",
    "desc": "1対1で再現されたゲーム用の20面ダイスは、金属素材をレーザーで・刻して作られ、手触りは非常に良いです。それを持つと、より良い数値を出せるような気がします。",
    "quality": "RARE",
    "hobby_flag": [
      "Genet",
      "toy",
      "metal",
      "game"
    ],
    "value": 40,
    "assets": {
      "icon": "/Icon/ImitationGift/gift4004.webp"
    }
  },
  "Item_gift_4025": {
    "id": "Item_gift_4025",
    "name": "劇場のシーズンチケット",
    "desc": "アーシャ大劇場のVIPシーズンチケット。新シーズンのすべての演目をプライベート感のあるボックス席から無料で鑑賞できる",
    "quality": "EPIC",
    "hobby_flag": [
      "Genet",
      "rarity",
      "restrictedGoods"
    ],
    "value": 40,
    "assets": {
      "icon": "/Icon/ImitationGift/gift4025.webp"
    }
  },
  "Item_gift_4005": {
    "id": "Item_gift_4005",
    "name": "精密な整備オイル",
    "desc": "一般的な武器の整備用オイル。定期的に使用することで、武器の耐久年数を延ばすことができる",
    "quality": "RARE",
    "hobby_flag": [
      "Genet",
      "everydayObjects"
    ],
    "value": 40,
    "assets": {
      "icon": "/Icon/ImitationGift/gift4005.webp"
    }
  },
  "Item_gift_4026": {
    "id": "Item_gift_4026",
    "name": "シャーリー抱き枕",
    "desc": "シャーリーの姿が描かれた抱き枕、ヴォイドの好みにぴったり。この抱き枕があれば、彼女は安心して眠ることができる。",
    "quality": "EPIC",
    "hobby_flag": [
      "Genet",
      "collection",
      "rarity",
      "everydayObjects"
    ],
    "value": 40,
    "assets": {
      "icon": "/Icon/ImitationGift/gift4026.webp"
    }
  },
  "Item_gift_4027": {
    "id": "Item_gift_4027",
    "name": "権限者抱き枕",
    "desc": "権限者の姿が描かれた抱き枕、ヴォイドの好みにピッタリ。この抱き枕があれば、彼女は安心して眠ることができる。",
    "quality": "EPIC",
    "hobby_flag": [
      "Genet",
      "collection",
      "rarity",
      "everydayObjects"
    ],
    "value": 40,
    "assets": {
      "icon": "/Icon/ImitationGift/gift4027.webp"
    }
  }
}