{
	"name": "Huma",
	"type": "ITEM_TYPE_MATRIX",
	"description": "El instinto por ver la luz guio a los pichones fuera de sus cascarones.",
	"icon": "icon_matrix_SSR10_512",
	"gachaIcon": "icon_matrix_SSR10_512",
	"rarity": "SSR",
	"set": [
		{
			"2": "Impactar objetivos con habilidades de evasión los hace sangrar, lo que inflige daño equivalente al **15%**/19%/22.5%/26% del ATQ cada segundo durante **5** segundos.",
			"4": "Reduce el ATQ de todos los objetivos en un radio de **8** metros que estén recibiendo daño prolongado un **10%**/12%/13%/15%. Solo se aplica el efecto del nivel más alto cuando se obtiene repetidamente."
		}
	],
	"id": "matrix_SSR10_1"
}