{
	"TestAvatarFrame01": {
		"name": "Metal",
		"icon": "https://raw.githubusercontent.com/FortOfFans/ToF.github.io/webp/Icon/AvatarFrame/AvatarFrame_02.webp"
	},
	"TestAvatarFrame02": {
		"name": "Wreath",
		"icon": "https://raw.githubusercontent.com/FortOfFans/ToF.github.io/webp/Icon/AvatarFrame/AvatarFrame_01.webp"
	},
	"AvatarFrame03": {
		"name": "Shining Star",
		"icon": "https://raw.githubusercontent.com/FortOfFans/ToF.github.io/webp/Icon/AvatarFrame/AvatarFrame_shali.webp"
	},
	"AvatarFrame04": {
		"name": "Leader of Astra",
		"icon": "https://raw.githubusercontent.com/FortOfFans/ToF.github.io/webp/Icon/AvatarFrame/AvatarFrame_xiazuo.webp"
	},
	"AvatarFrame05": {
		"name": "Mandrill",
		"icon": "https://raw.githubusercontent.com/FortOfFans/ToF.github.io/webp/Icon/AvatarFrame/AvatarFrame_xuxubaobao.webp"
	},
	"kefu": {
		"name": "Layanan Pelanggan",
		"icon": "https://raw.githubusercontent.com/FortOfFans/ToF.github.io/webp/Icon/AvatarFrame/AvatarFrame_naimeixisi.webp"
	},
	"AvatarFrame06": {
		"name": "Pure Illusion",
		"icon": "https://raw.githubusercontent.com/FortOfFans/ToF.github.io/webp/Icon/AvatarFrame/AvatarFrame_fulijia.webp"
	},
	"AvatarFrame07": {
		"name": "Call of the Dead",
		"icon": "https://raw.githubusercontent.com/FortOfFans/ToF.github.io/webp/Icon/AvatarFrame/AvatarFrame_naimeixisi.webp"
	},
	"AvatarFrame08": {
		"name": "Absolute Authority",
		"icon": "https://raw.githubusercontent.com/FortOfFans/ToF.github.io/webp/Icon/AvatarFrame/AvatarFrame_xier.webp"
	},
	"AvatarFrame09": {
		"name": "Homeward Wings",
		"icon": "https://raw.githubusercontent.com/FortOfFans/ToF.github.io/webp/Icon/AvatarFrame/AvatarFrame_yixisi.webp"
	},
	"AvatarFrame10": {
		"name": "Lightning Strike",
		"icon": "https://raw.githubusercontent.com/FortOfFans/ToF.github.io/webp/Icon/AvatarFrame/AvatarFrame_valkiri.webp"
	},
	"AvatarFrame11": {
		"name": "Eksekutor",
		"icon": "https://raw.githubusercontent.com/FortOfFans/ToF.github.io/webp/Icon/AvatarFrame/AvatarFrame_haijiade.webp"
	},
	"AvatarFrame12": {
		"name": "Tower's Core",
		"icon": "https://raw.githubusercontent.com/FortOfFans/ToF.github.io/webp/Icon/AvatarFrame/AvatarFrame_hotta.webp"
	},
	"meilier": {
		"name": "Meryl",
		"icon": "https://raw.githubusercontent.com/FortOfFans/ToF.github.io/webp/Icon/AvatarFrame/AvatarFrame_shali.webp"
	},
	"AvatarFrame13": {
		"name": "Expert Creator",
		"icon": "https://raw.githubusercontent.com/FortOfFans/ToF.github.io/webp/Icon/AvatarFrame/AvatarFrame_chuangzuodaren.webp"
	},
	"AvatarFrame14": {
		"name": "SciFi World",
		"icon": "https://raw.githubusercontent.com/FortOfFans/ToF.github.io/webp/Icon/AvatarFrame/AvatarFrame_kehuanshijie.webp"
	},
	"AvatarFrame15": {
		"name": "Assistant",
		"icon": "https://raw.githubusercontent.com/FortOfFans/ToF.github.io/webp/Icon/AvatarFrame/AvatarFrame_tata.webp"
	},
	"AvatarFrame16": {
		"name": "Hanging Amusement Park",
		"icon": "https://raw.githubusercontent.com/FortOfFans/ToF.github.io/webp/Icon/AvatarFrame/AvatarFrame_kongzhongleyuan.webp"
	},
	"AvatarFrame17": {
		"name": "Otak Cuan",
		"icon": "https://raw.githubusercontent.com/FortOfFans/ToF.github.io/webp/Icon/AvatarFrame/AvatarFrame_Coffee.webp"
	},
	"AvatarFrame18": {
		"name": "Top Construction Team",
		"icon": "https://raw.githubusercontent.com/FortOfFans/ToF.github.io/webp/Icon/AvatarFrame/AvatarFrame_tajian.webp"
	},
	"AvatarFrame19": {
		"name": "Dawn: Morning Light",
		"icon": "https://raw.githubusercontent.com/FortOfFans/ToF.github.io/webp/Icon/AvatarFrame/AvatarFrame_make.webp"
	},
	"AvatarFrame20": {
		"name": "Moon: Crossing Light",
		"icon": "https://raw.githubusercontent.com/FortOfFans/ToF.github.io/webp/Icon/AvatarFrame/AvatarFrame_baiyuekui.webp"
	},
	"AvatarFrame21": {
		"name": "Peace and Joy",
		"icon": "https://raw.githubusercontent.com/FortOfFans/ToF.github.io/webp/Icon/AvatarFrame/AvatarFrame_21.webp"
	},
	"AvatarFrame22": {
		"name": "Sedikit Mabuk",
		"icon": "https://raw.githubusercontent.com/FortOfFans/ToF.github.io/webp/Icon/AvatarFrame/AvatarFrame_Valentine.webp"
	},
	"AvatarFrame23": {
		"name": "Rekan",
		"icon": "https://raw.githubusercontent.com/FortOfFans/ToF.github.io/webp/Icon/AvatarFrame/AvatarFrame_023.webp"
	},
	"AvatarFrame24": {
		"name": "Tubuh Luar",
		"icon": "https://raw.githubusercontent.com/FortOfFans/ToF.github.io/webp/Icon/AvatarFrame/AvatarFrame_024.webp"
	},
	"AvatarFrame25": {
		"name": "Island Fantasy",
		"icon": "https://raw.githubusercontent.com/FortOfFans/ToF.github.io/webp/Icon/AvatarFrame/AvatarFrame_rengongdao_feimao.webp"
	},
	"AvatarFrame26": {
		"name": "Knight of Night",
		"icon": "https://raw.githubusercontent.com/FortOfFans/ToF.github.io/webp/Icon/AvatarFrame/AvatarFrame_rengongdao_heimao.webp"
	},
	"AvatarFrame27": {
		"name": "Harta Karun Pawpaw",
		"icon": "https://raw.githubusercontent.com/FortOfFans/ToF.github.io/webp/Icon/AvatarFrame/AvatarFrame_rengongdao_huli.webp"
	},
	"AvatarFrame28": {
		"name": "Pumpkin Night",
		"icon": "https://raw.githubusercontent.com/FortOfFans/ToF.github.io/webp/Icon/AvatarFrame/AvatarFrame_rengongdao_nangua.webp"
	},
	"AvatarFrame29": {
		"name": "Memori",
		"icon": "https://raw.githubusercontent.com/FortOfFans/ToF.github.io/webp/Icon/AvatarFrame/AvatarFrame_rengongdao_wugui.webp"
	},
	"AvatarFrame30": {
		"name": "Gaze Mirroria",
		"icon": "https://raw.githubusercontent.com/FortOfFans/ToF.github.io/webp/Icon/AvatarFrame/AvatarFrame_30.webp"
	},
	"AvatarFrame31": {
		"name": "Steel Lizard Charge",
		"icon": "https://raw.githubusercontent.com/FortOfFans/ToF.github.io/webp/Icon/AvatarFrame/AvatarFrame_31.webp"
	},
	"AvatarFrame32": {
		"name": "Off-Balance Dancer",
		"icon": "https://raw.githubusercontent.com/FortOfFans/ToF.github.io/webp/Icon/AvatarFrame/AvatarFrame_32.webp"
	},
	"AvatarFrame33": {
		"name": "Mimpi Indah",
		"icon": "https://raw.githubusercontent.com/FortOfFans/ToF.github.io/webp/Icon/AvatarFrame/AvatarFrame_33.webp"
	},
	"AvatarFrame34": {
		"name": "Journey Nursery Rhyme",
		"icon": "https://raw.githubusercontent.com/FortOfFans/ToF.github.io/webp/Icon/AvatarFrame/AvatarFrame_34.webp"
	},
	"AvatarFrame35": {
		"name": "Cordate Jellybean",
		"icon": "https://raw.githubusercontent.com/FortOfFans/ToF.github.io/webp/Icon/AvatarFrame/AvatarFrame_35.webp"
	},
	"AvatarFrame36": {
		"name": "Naughty Trails",
		"icon": "https://raw.githubusercontent.com/FortOfFans/ToF.github.io/webp/Icon/AvatarFrame/AvatarFrame_36.webp"
	},
	"AvatarFrame37": {
		"name": "Aroma of Leaves",
		"icon": "https://raw.githubusercontent.com/FortOfFans/ToF.github.io/webp/Icon/AvatarFrame/AvatarFrame_37.webp"
	},
	"AvatarFrame38": {
		"name": "Pure White Conversion",
		"icon": "https://raw.githubusercontent.com/FortOfFans/ToF.github.io/webp/Icon/AvatarFrame/AvatarFrame_38.webp"
	},
	"AvatarFrame39": {
		"name": "Kepala Pelindung Lingkungan",
		"icon": "https://raw.githubusercontent.com/FortOfFans/ToF.github.io/webp/Icon/AvatarFrame/AvatarFrame_39.webp"
	},
	"AvatarFrame40": {
		"name": "Salty Wave",
		"icon": "https://raw.githubusercontent.com/FortOfFans/ToF.github.io/webp/Icon/AvatarFrame/AvatarFrame_40.webp"
	},
	"AvatarFrame41": {
		"name": "Summer Cool",
		"icon": "https://raw.githubusercontent.com/FortOfFans/ToF.github.io/webp/Icon/AvatarFrame/AvatarFrame_41.webp"
	},
	"AvatarFrame42": {
		"name": "Sparkler Bouquet",
		"icon": "https://raw.githubusercontent.com/FortOfFans/ToF.github.io/webp/Icon/AvatarFrame/AvatarFrame_42.webp"
	},
	"AvatarFrame43": {
		"name": "Nurse Trainee",
		"icon": "https://raw.githubusercontent.com/FortOfFans/ToF.github.io/webp/Icon/AvatarFrame/AvatarFrame_43.webp"
	},
	"AvatarFrame44": {
		"name": "Fantasy Park",
		"icon": "https://raw.githubusercontent.com/FortOfFans/ToF.github.io/webp/Icon/AvatarFrame/AvatarFrame_44.webp"
	},
	"AvatarFrame45": {
		"name": "Friend Astray",
		"icon": "https://raw.githubusercontent.com/FortOfFans/ToF.github.io/webp/Icon/AvatarFrame/AvatarFrame_45.webp"
	},
	"AvatarFrame46": {
		"name": "Watermelon Feast",
		"icon": "https://raw.githubusercontent.com/FortOfFans/ToF.github.io/webp/Icon/AvatarFrame/AvatarFrame_46.webp"
	},
	"AvatarFrame47": {
		"name": "Perhatian Bersama",
		"icon": "https://raw.githubusercontent.com/FortOfFans/ToF.github.io/webp/Icon/AvatarFrame/AvatarFrame_47.webp"
	},
	"AvatarFrame48": {
		"name": "Tanggung Jawab Penegak Kedisiplinan",
		"icon": "https://raw.githubusercontent.com/FortOfFans/ToF.github.io/webp/Icon/AvatarFrame/AvatarFrame_48.webp"
	},
	"AvatarFrame49": {
		"name": "Kerja Paruh Waktu",
		"icon": "https://raw.githubusercontent.com/FortOfFans/ToF.github.io/webp/Icon/AvatarFrame/AvatarFrame_49.webp"
	},
	"AvatarFrame50": {
		"name": "Nikmati Masa Sekarang",
		"icon": "https://raw.githubusercontent.com/FortOfFans/ToF.github.io/webp/Icon/AvatarFrame/AvatarFrame_50.webp"
	},
	"AvatarFrame51": {
		"name": "Pemburu Kecepatan",
		"icon": "https://raw.githubusercontent.com/FortOfFans/ToF.github.io/webp/Icon/AvatarFrame/AvatarFrame_51.webp"
	},
	"AvatarFrame52": {
		"name": "Pola Rumit",
		"icon": "https://raw.githubusercontent.com/FortOfFans/ToF.github.io/webp/Icon/AvatarFrame/AvatarFrame_52.webp"
	},
	"AvatarFrame53": {
		"name": "Panen Tahunan",
		"icon": "https://raw.githubusercontent.com/FortOfFans/ToF.github.io/webp/Icon/AvatarFrame/AvatarFrame_53.webp"
	},
	"AvatarFrame54": {
		"name": "Malam Keceriaan",
		"icon": "https://raw.githubusercontent.com/FortOfFans/ToF.github.io/webp/Icon/AvatarFrame/AvatarFrame_54.webp"
	},
	"AvatarFrame55": {
		"name": "Kehormatan Nelayan",
		"icon": "https://raw.githubusercontent.com/FortOfFans/ToF.github.io/webp/Icon/AvatarFrame/AvatarFrame_55.webp"
	},
	"AvatarFrame56": {
		"name": "Urutan Pembersihan",
		"icon": "https://raw.githubusercontent.com/FortOfFans/ToF.github.io/webp/Icon/AvatarFrame/AvatarFrame_56.webp"
	},
	"AvatarFrame57": {
		"name": "Blood Moon",
		"icon": "https://raw.githubusercontent.com/FortOfFans/ToF.github.io/webp/Icon/AvatarFrame/AvatarFrame_57.webp"
	},
	"AvatarFrame58": {
		"name": "Windchaser",
		"icon": "https://raw.githubusercontent.com/FortOfFans/ToF.github.io/webp/Icon/AvatarFrame/AvatarFrame_58.webp"
	},
	"AvatarFrame59": {
		"name": "DNT",
		"icon": "https://raw.githubusercontent.com/FortOfFans/ToF.github.io/webp/Icon/AvatarFrame/AvatarFrame_59.webp"
	},
	"AvatarFrame_60": {
		"name": "Stylish Straw Hat",
		"icon": "https://raw.githubusercontent.com/FortOfFans/ToF.github.io/webp/Icon/AvatarFrame/AvatarFrame_60.webp"
	},
	"AvatarFrame_61": {
		"name": "Setahun Penuh Kebahagiaan",
		"icon": "https://raw.githubusercontent.com/FortOfFans/ToF.github.io/webp/Icon/AvatarFrame/AvatarFrame_61.webp"
	},
	"AvatarFrame_62": {
		"name": "Kue dan Pesta",
		"icon": "https://raw.githubusercontent.com/FortOfFans/ToF.github.io/webp/Icon/AvatarFrame/AvatarFrame_62.webp"
	},
	"AvatarFrame_63": {
		"name": "Momen Penuh Warna",
		"icon": "https://raw.githubusercontent.com/FortOfFans/ToF.github.io/webp/Icon/AvatarFrame/AvatarFrame_63.webp"
	},
	"AvatarFrame_64": {
		"name": "Bintang di Laut",
		"icon": "https://raw.githubusercontent.com/FortOfFans/ToF.github.io/webp/Icon/AvatarFrame/AvatarFrame_64.webp"
	},
	"AvatarFrame_65": {
		"name": "Raungan Naga",
		"icon": "https://raw.githubusercontent.com/FortOfFans/ToF.github.io/webp/Icon/AvatarFrame/AvatarFrame_65.webp"
	},
	"AvatarFrame_66": {
		"name": "Pelayaran Alam Biru",
		"icon": "https://raw.githubusercontent.com/FortOfFans/ToF.github.io/webp/Icon/AvatarFrame/AvatarFrame_66.webp"
	},
	"AvatarFrame_67": {
		"name": "Petualangan Impian",
		"icon": "https://raw.githubusercontent.com/FortOfFans/ToF.github.io/webp/Icon/AvatarFrame/AvatarFrame_67.webp"
	},
	"AvatarFrame_68": {
		"name": "Konsensus",
		"icon": "https://raw.githubusercontent.com/FortOfFans/ToF.github.io/webp/Icon/AvatarFrame/AvatarFrame_68.webp"
	},
	"AvatarFrame_69": {
		"name": "Reindeer & Bell",
		"icon": "https://raw.githubusercontent.com/FortOfFans/ToF.github.io/webp/Icon/AvatarFrame/AvatarFrame_69.webp"
	},
	"AvatarFrame_70": {
		"name": "Commitment",
		"icon": "https://raw.githubusercontent.com/FortOfFans/ToF.github.io/webp/Icon/AvatarFrame/AvatarFrame_70.webp"
	},
	"AvatarFrame_Overseas_1": {
		"name": "Penemu Terbaik",
		"icon": "https://raw.githubusercontent.com/FortOfFans/ToF.github.io/webpOverSea/Icon/AvatarFrame/AvatarFrame_TX_BestTower.webp"
	},
	"AvatarFrame_Overseas_2": {
		"name": "Illusory Link",
		"icon": "https://raw.githubusercontent.com/FortOfFans/ToF.github.io/webpOverSea/Icon/AvatarFrame/AvatarFrame_TX_Xuhuan.webp"
	},
	"AvatarFrame_Overseas_3": {
		"name": "Raging Sands",
		"icon": "https://raw.githubusercontent.com/FortOfFans/ToF.github.io/webpOverSea/Icon/AvatarFrame/AvatarFrame_TX_twitch.webp"
	},
	"AvatarFrame_Overseas_4": {
		"name": "Selamat Datang Di Vera",
		"icon": "https://raw.githubusercontent.com/FortOfFans/ToF.github.io/webpOverSea/Icon/AvatarFrame/AvatarFrame_TX_steam.webp"
	},
	"AvatarFrame_Overseas_5": {
		"name": "Penggemar Diskon",
		"icon": "https://raw.githubusercontent.com/FortOfFans/ToF.github.io/webpOverSea/Icon/AvatarFrame/AvatarFrame_TX_off.webp"
	},
	"AvatarFrame_Overseas_6": {
		"name": "Hitung Mundur",
		"icon": "https://raw.githubusercontent.com/FortOfFans/ToF.github.io/webpOverSea/Icon/AvatarFrame/AvatarFrame_TX_gift.webp"
	},
	"AvatarFrameiw_01": {
		"icon": "https://raw.githubusercontent.com/FortOfFans/ToF.github.io/webp/Icon/AvatarFrame/AvatarFrame_iw_01.webp"
	},
	"AvatarFramekr_01": {
		"name": "DNT",
		"icon": "https://raw.githubusercontent.com/FortOfFans/ToF.github.io/webpOverSea/Icon/AvatarFrame/AvatarFramekr_01.webp"
	},
	"CN_AvatarFrame_1": {
		"name": "Semangat Jumat",
		"icon": "https://raw.githubusercontent.com/FortOfFans/ToF.github.io/webp/Icon/AvatarFrame/AvatarFrame_tencent_05.webp"
	},
	"CN_AvatarFrame_2": {
		"name": "Langkah Tak Terbelenggu",
		"icon": "https://raw.githubusercontent.com/FortOfFans/ToF.github.io/webp/Icon/AvatarFrame/AvatarFrame_Overseas_Anniversary01.webp"
	},
	"CN_AvatarFrame_3": {
		"name": "Nyala Api Musim Dingin",
		"icon": "https://raw.githubusercontent.com/FortOfFans/ToF.github.io/webp/Icon/AvatarFrame/CN_AvatarFrame_3.webp"
	},
	"CN_AvatarFrame_4": {
		"name": "Kuas Bermekaran",
		"icon": "https://raw.githubusercontent.com/FortOfFans/ToF.github.io/webp/Icon/AvatarFrame/CN_AvatarFrame_4.webp"
	},
	"CN_AvatarFrame_5": {
		"name": "Renungan Musim Dingin",
		"icon": "https://raw.githubusercontent.com/FortOfFans/ToF.github.io/webp/Icon/AvatarFrame/CN_AvatarFrame_5.webp"
	},
	"AvatarFrame_tencent_1": {
		"name": "Kreator Luar Biasa",
		"icon": "https://raw.githubusercontent.com/FortOfFans/ToF.github.io/webpOverSea/Icon/AvatarFrame/AvatarFrame_TX_Creatower.webp"
	},
	"AvatarFrame_tencent_2": {
		"name": "Master Kreator",
		"icon": "https://raw.githubusercontent.com/FortOfFans/ToF.github.io/webpOverSea/Icon/AvatarFrame/AvatarFrame_TX_CreatowerMaster.webp"
	},
	"AvatarFrame_tencent_3": {
		"name": "CreatowerofFantasy",
		"icon": "https://raw.githubusercontent.com/FortOfFans/ToF.github.io/webpOverSea/Icon/AvatarFrame/AvatarFrame_TX_CreatowerOfFantasy.webp"
	},
	"AvatarFrameiw_02": {
		"icon": "https://raw.githubusercontent.com/FortOfFans/ToF.github.io/webpOverSea/Icon/AvatarFrame/AvatarFrameiw_02.webp"
	},
	"AvatarFrameiw_03": {
		"icon": "https://raw.githubusercontent.com/FortOfFans/ToF.github.io/webpOverSea/Icon/AvatarFrame/AvatarFrameiw_03.webp"
	},
	"AvatarFrameiw_04": {
		"icon": "https://raw.githubusercontent.com/FortOfFans/ToF.github.io/webpOverSea/Icon/AvatarFrame/AvatarFrameiw_04.webp"
	},
	"AvatarFrame_korea_1": {
		"name": "DNT",
		"icon": "https://raw.githubusercontent.com/FortOfFans/ToF.github.io/webpOverSea/Icon/AvatarFrame/AvatarFrame_korea_1.webp"
	},
	"AvatarFrame_koreafestival_1": {
		"name": "DNT",
		"icon": "https://raw.githubusercontent.com/FortOfFans/ToF.github.io/webpOverSea/Icon/AvatarFrame/AvatarFrame_koreafestival_1.webp"
	},
	"AvatarFrame_tencent_02": {
		"name": "Legenda Lapangan",
		"icon": "https://raw.githubusercontent.com/FortOfFans/ToF.github.io/webpOverSea/Icon/AvatarFrame/AvatarFrame_tencent_2.webp"
	},
	"AvatarFrame_iw_1": {
		"name": "Menendang bola itu urusannya bukan cuma tentang gerakan kakimu.",
		"icon": "https://raw.githubusercontent.com/FortOfFans/ToF.github.io/webpOverSea/Icon/AvatarFrame/AvatarFrame_iw_1.webp"
	},
	"AvatarFrame_iwplayfestival_1": {
		"name": "DNT",
		"icon": "https://raw.githubusercontent.com/FortOfFans/ToF.github.io/webpOverSea/Icon/AvatarFrame/AvatarFrame_iwplayfestival_1.webp"
	},
	"AvatarFrame_tencentfestival_3": {
		"name": "Renungan Musim Dingin",
		"icon": "https://raw.githubusercontent.com/FortOfFans/ToF.github.io/webpOverSea/Icon/AvatarFrame/AvatarFrame_tencentfestival_3.webp"
	},
	"AvatarFrame_tencentfestival_4": {
		"name": "Petualangan Tahun Baru",
		"icon": "https://raw.githubusercontent.com/FortOfFans/ToF.github.io/webpOverSea/Icon/AvatarFrame/AvatarFrame_tencentfestival_4.webp"
	},
	"AvatarFrame_HalfAnniversary_os_1": {
		"name": "Berdampingan",
		"icon": "https://raw.githubusercontent.com/FortOfFans/ToF.github.io/webpOverSea/Icon/AvatarFrame/AvatarFrame_HalfAnniversary_os_1.webp"
	},
	"AvatarFrame_tencentugc_os_1": {
		"name": "Kota Cyberpunk",
		"icon": "https://raw.githubusercontent.com/FortOfFans/ToF.github.io/webpOverSea/Icon/AvatarFrame/AvatarFrame_tencentugc_os_1.webp"
	},
	"AvatarFrame_71": {
		"name": "Pesta Kelinci",
		"icon": "https://raw.githubusercontent.com/FortOfFans/ToF.github.io/webp/Icon/AvatarFrame/AvatarFrame_71.webp"
	},
	"AvatarFrame_72": {
		"name": "Bunny Surprise",
		"icon": "https://raw.githubusercontent.com/FortOfFans/ToF.github.io/webp/Icon/AvatarFrame/AvatarFrame_72.webp"
	},
	"AvatarFrame_73": {
		"name": "Primal Judgement",
		"icon": "https://raw.githubusercontent.com/FortOfFans/ToF.github.io/webp/Icon/AvatarFrame/AvatarFrame_73.webp"
	},
	"AvatarFrame_74": {
		"name": "Percobaan Platinum Armor",
		"icon": "https://raw.githubusercontent.com/FortOfFans/ToF.github.io/webp/Icon/AvatarFrame/AvatarFrame_74.webp"
	},
	"AvatarFrame_75": {
		"name": "Shining Sea",
		"icon": "https://raw.githubusercontent.com/FortOfFans/ToF.github.io/webp/Icon/AvatarFrame/AvatarFrame_75.webp"
	},
	"AvatarFrame_76": {
		"name": "Taste of Destiny",
		"icon": "https://raw.githubusercontent.com/FortOfFans/ToF.github.io/webp/Icon/AvatarFrame/AvatarFrame_76.webp"
	},
	"AvatarFrame_77": {
		"name": "Bayangan Mendekat",
		"icon": "https://raw.githubusercontent.com/FortOfFans/ToF.github.io/webp/Icon/AvatarFrame/AvatarFrame_77.webp"
	},
	"AvatarFrame_78": {
		"name": "Sopan Santun",
		"icon": "https://raw.githubusercontent.com/FortOfFans/ToF.github.io/webp/Icon/AvatarFrame/AvatarFrame_78.webp"
	},
	"AvatarFrame_79": {
		"name": "Kedatangan Kembali",
		"icon": "https://raw.githubusercontent.com/FortOfFans/ToF.github.io/webp/Icon/AvatarFrame/AvatarFrame_79.webp"
	},
	"AvatarFrame_80": {
		"name": "Surface Scanner",
		"icon": "https://raw.githubusercontent.com/FortOfFans/ToF.github.io/webp/Icon/AvatarFrame/AvatarFrame_80.webp"
	},
	"AvatarFrame_81": {
		"name": "Angin Dan Lembah",
		"icon": "https://raw.githubusercontent.com/FortOfFans/ToF.github.io/webp/Icon/AvatarFrame/AvatarFrame_81.webp"
	},
	"AvatarFrame_82": {
		"name": "Keberuntungan Vermilion",
		"icon": "https://raw.githubusercontent.com/FortOfFans/ToF.github.io/webp/Icon/AvatarFrame/AvatarFrame_82.webp"
	},
	"AvatarFrame_83": {
		"name": "Layangan Micius",
		"icon": "https://raw.githubusercontent.com/FortOfFans/ToF.github.io/webp/Icon/AvatarFrame/AvatarFrame_83.webp"
	},
	"AvatarFrame_85": {
		"name": "Bagai Tangisan",
		"icon": "https://raw.githubusercontent.com/FortOfFans/ToF.github.io/webp/Icon/AvatarFrame/AvatarFrame_85.webp"
	},
	"AvatarFrame_86": {
		"name": "Goresan Kuas",
		"icon": "https://raw.githubusercontent.com/FortOfFans/ToF.github.io/webp/Icon/AvatarFrame/AvatarFrame_86.webp"
	},
	"AvatarFrame_87": {
		"name": "Lukisan",
		"icon": "https://raw.githubusercontent.com/FortOfFans/ToF.github.io/webp/Icon/AvatarFrame/AvatarFrame_87.webp"
	},
	"AvatarFrame_88": {
		"name": "Kotak Rias Peri",
		"icon": "https://raw.githubusercontent.com/FortOfFans/ToF.github.io/webp/Icon/AvatarFrame/AvatarFrame_88.webp"
	},
	"AvatarFrame_89": {
		"name": "Maple & Jade",
		"icon": "https://raw.githubusercontent.com/FortOfFans/ToF.github.io/webp/Icon/AvatarFrame/AvatarFrame_89.webp"
	},
	"AvatarFrame_90": {
		"name": "Atas Nama Keprajuritan",
		"icon": "https://raw.githubusercontent.com/FortOfFans/ToF.github.io/webp/Icon/AvatarFrame/AvatarFrame_90.webp"
	},
	"AvatarFrame_91": {
		"name": "Reuni Bulan Purnama",
		"icon": "https://raw.githubusercontent.com/FortOfFans/ToF.github.io/webp/Icon/AvatarFrame/AvatarFrame_91.webp"
	},
	"AvatarFrame_92": {
		"name": "Langit Jernih Di Taman Bambu",
		"icon": "https://raw.githubusercontent.com/FortOfFans/ToF.github.io/webp/Icon/AvatarFrame/AvatarFrame_92.webp"
	},
	"AvatarFrame_93": {
		"name": "Belenggu Perunggu",
		"icon": "https://raw.githubusercontent.com/FortOfFans/ToF.github.io/webp/Icon/AvatarFrame/AvatarFrame_93.webp"
	},
	"AvatarFrame_94": {
		"name": "Awan Berseri",
		"icon": "https://raw.githubusercontent.com/FortOfFans/ToF.github.io/webp/Icon/AvatarFrame/AvatarFrame_94.webp"
	},
	"AvatarFrame_95": {
		"name": "Sprigy Pemalu",
		"icon": "https://raw.githubusercontent.com/FortOfFans/ToF.github.io/webp/Icon/AvatarFrame/AvatarFrame_95.webp"
	},
	"AvatarFrame_korea_shequnos_01": {
		"name": "DNT",
		"icon": "https://raw.githubusercontent.com/FortOfFans/ToF.github.io/webpOverSea/Icon/AvatarFrame/AvatarFrame_korea_shequnos_01.webp"
	},
	"AvatarFrame_txcreatos_01": {
		"name": "Hutan Penuh Misteri",
		"icon": "https://raw.githubusercontent.com/FortOfFans/ToF.github.io/webpOverSea/Icon/AvatarFrame/AvatarFrame_txcreatos_01.webp"
	},
	"AvatarFrame_txcreatos_02": {
		"name": "Perintis Aida",
		"icon": "https://raw.githubusercontent.com/FortOfFans/ToF.github.io/webpOverSea/Icon/AvatarFrame/AvatarFrame_txcreatos_02.webp"
	},
	"AvatarFrame_txtaqing_os01": {
		"name": "Cahaya Ombak",
		"icon": "https://raw.githubusercontent.com/FortOfFans/ToF.github.io/webpOverSea/Icon/AvatarFrame/AvatarFrame_txtaqing_os01.webp"
	},
	"AvatarFrame_epic_os01": {
		"name": "Epic Gamer",
		"icon": "https://raw.githubusercontent.com/FortOfFans/ToF.github.io/webpOverSea/Icon/AvatarFrame/AvatarFrame_epic_os01.webp"
	},
	"AvatarFrame_tencentfestival_1": {
		"name": "Logam Cemerlang",
		"icon": "https://raw.githubusercontent.com/FortOfFans/ToF.github.io/webpOverSea/Icon/AvatarFrame/AvatarFrame_tencentfestival_1.webp"
	},
	"AvatarFrame_tencentfestival_2": {
		"name": "Gemerlap Neon",
		"icon": "https://raw.githubusercontent.com/FortOfFans/ToF.github.io/webpOverSea/Icon/AvatarFrame/AvatarFrame_tencentfestival_2.webp"
	},
	"AvatarFrame_tencentdiqu_01": {
		"name": "Bunga Musim Panas",
		"icon": "https://raw.githubusercontent.com/FortOfFans/ToF.github.io/webpOverSea/Icon/AvatarFrame/AvatarFrame_tencentdiqu_01.webp"
	},
	"AvatarFrame_tencentugc_os_2": {
		"name": "Lautan Indigo",
		"icon": "https://raw.githubusercontent.com/FortOfFans/ToF.github.io/webpOverSea/Icon/AvatarFrame/AvatarFrame_tencentugc_os_2.webp"
	},
	"AvatarFrame_suoni": {
		"name": "Waktunya Permainan",
		"icon": "https://raw.githubusercontent.com/FortOfFans/ToF.github.io/webp/Icon/AvatarFrame/AvatarFrame_suoni.webp"
	},
	"AvatarFrame_txcreatos_03": {
		"name": "Reruntuhan Misterius",
		"icon": "https://raw.githubusercontent.com/FortOfFans/ToF.github.io/webpOverSea/Icon/AvatarFrame/AvatarFrame_txcreatos_03.webp"
	},
	"AvatarFrame_Galaxy_01": {
		"name": "Gamer Galaksi",
		"icon": "https://raw.githubusercontent.com/FortOfFans/ToF.github.io/webpOverSea/Icon/AvatarFrame/AvatarFrame_Galaxy_01.webp"
	},
	"AvatarFrame_iwplayoffline_01": {
		"name": "DNT",
		"icon": "https://raw.githubusercontent.com/FortOfFans/ToF.github.io/webpOverSea/Icon/AvatarFrame/AvatarFrame_iwplayoffline_01.webp"
	},
	"AvatarFrame_txcreatos_04": {
		"name": "Dimensi Asing",
		"icon": "https://raw.githubusercontent.com/FortOfFans/ToF.github.io/webpOverSea/Icon/AvatarFrame/AvatarFrame_txcreatos_04.webp"
	},
	"AvatarFrame_txAnniversary01": {
		"name": "Pertemuan Paviliun Jade",
		"icon": "https://raw.githubusercontent.com/FortOfFans/ToF.github.io/webpOverSea/Icon/AvatarFrame/AvatarFrame_txAnniversary01.webp"
	},
	"AvatarFrame_txAnniversary02": {
		"name": "Pertemuan Paviliun Jade (Crescent)",
		"icon": "https://raw.githubusercontent.com/FortOfFans/ToF.github.io/webpOverSea/Icon/AvatarFrame/AvatarFrame_txAnniversary02.webp"
	},
	"AvatarFrame_txAnniversary03": {
		"name": "Pertemuan Paviliun Jade (Full)",
		"icon": "https://raw.githubusercontent.com/FortOfFans/ToF.github.io/webpOverSea/Icon/AvatarFrame/AvatarFrame_txAnniversary03.webp"
	},
	"AvatarFrame_txcreatos_05": {
		"name": "PerintisAida 2",
		"icon": "https://raw.githubusercontent.com/FortOfFans/ToF.github.io/webpOverSea/Icon/AvatarFrame/AvatarFrame_txcreatos_05.webp"
	},
	"AvatarFrame_Overseas_Anniversary01": {
		"name": "Langkah Tak Terbelenggu",
		"icon": "https://raw.githubusercontent.com/FortOfFans/ToF.github.io/webpOverSea/Icon/AvatarFrame/AvatarFrame_Overseas_Anniversary01.webp"
	},
	"AvatarFrame_PlayStation_01": {
		"name": "Dalam Kabut",
		"icon": "https://raw.githubusercontent.com/FortOfFans/ToF.github.io/webpOverSea/Icon/AvatarFrame/AvatarFrame_PlayStation_01.webp"
	},
	"AvatarFrame_96": {
		"name": "Awan Naga & Daun Jade",
		"icon": "https://raw.githubusercontent.com/FortOfFans/ToF.github.io/webp/Icon/AvatarFrame/AvatarFrame_96.webp"
	},
	"AvatarFrame_97": {
		"name": "Vas",
		"icon": "https://raw.githubusercontent.com/FortOfFans/ToF.github.io/webp/Icon/AvatarFrame/AvatarFrame_97.webp"
	},
	"AvatarFrame_98": {
		"name": "Kaca Mata Hitam Swag",
		"icon": "https://raw.githubusercontent.com/FortOfFans/ToF.github.io/webp/Icon/AvatarFrame/AvatarFrame_98.webp"
	},
	"AvatarFrame_99": {
		"name": "Langkah Awal Petualangan",
		"icon": "https://raw.githubusercontent.com/FortOfFans/ToF.github.io/webp/Icon/AvatarFrame/AvatarFrame_99.webp"
	},
	"AvatarFrame_100": {
		"name": "Menikmati Hidup",
		"icon": "https://raw.githubusercontent.com/FortOfFans/ToF.github.io/webp/Icon/AvatarFrame/AvatarFrame_100.webp"
	},
	"AvatarFrame_101": {
		"name": "Tegak",
		"icon": "https://raw.githubusercontent.com/FortOfFans/ToF.github.io/webp/Icon/AvatarFrame/AvatarFrame_101.webp"
	},
	"AvatarFrame_102": {
		"name": "Demi Zhuque",
		"icon": "https://raw.githubusercontent.com/FortOfFans/ToF.github.io/webp/Icon/AvatarFrame/AvatarFrame_102.webp"
	},
	"AvatarFrame_103": {
		"name": "Kuping Anabul",
		"icon": "https://raw.githubusercontent.com/FortOfFans/ToF.github.io/webp/Icon/AvatarFrame/AvatarFrame_103.webp"
	},
	"AvatarFrame_104": {
		"name": "Sobat Cilik",
		"icon": "https://raw.githubusercontent.com/FortOfFans/ToF.github.io/webp/Icon/AvatarFrame/AvatarFrame_104.webp"
	},
	"AvatarFrame_105": {
		"name": "Pita Sutra Biru",
		"icon": "https://raw.githubusercontent.com/FortOfFans/ToF.github.io/webp/Icon/AvatarFrame/AvatarFrame_105.webp"
	},
	"AvatarFrame_106": {
		"name": "Tulang",
		"icon": "https://raw.githubusercontent.com/FortOfFans/ToF.github.io/webp/Icon/AvatarFrame/AvatarFrame_106.webp"
	},
	"AvatarFrame_107": {
		"name": "Gumpalan Sutra",
		"icon": "https://raw.githubusercontent.com/FortOfFans/ToF.github.io/webp/Icon/AvatarFrame/AvatarFrame_107.webp"
	},
	"AvatarFrame_108": {
		"name": "Mulut Kegelapan",
		"icon": "https://raw.githubusercontent.com/FortOfFans/ToF.github.io/webp/Icon/AvatarFrame/AvatarFrame_108.webp"
	},
	"AvatarFrame_109": {
		"name": "Magic Harvest",
		"icon": "https://raw.githubusercontent.com/FortOfFans/ToF.github.io/webp/Icon/AvatarFrame/AvatarFrame_109.webp"
	},
	"AvatarFrame_110": {
		"name": "Domain Empat Simbol",
		"icon": "https://raw.githubusercontent.com/FortOfFans/ToF.github.io/webp/Icon/AvatarFrame/AvatarFrame_110.webp"
	},
	"AvatarFrame_111": {
		"icon": "https://raw.githubusercontent.com/FortOfFans/ToF.github.io/webp/Icon/AvatarFrame/AvatarFrame_111.webp"
	},
	"AvatarFrame_112": {
		"icon": "https://raw.githubusercontent.com/FortOfFans/ToF.github.io/webp/Icon/AvatarFrame/AvatarFrame_112.webp"
	},
	"AvatarFrame_113": {
		"icon": "https://raw.githubusercontent.com/FortOfFans/ToF.github.io/webp/Icon/AvatarFrame/AvatarFrame_113.webp"
	},
	"AvatarFrame_114": {
		"name": "Turu Halu",
		"icon": "https://raw.githubusercontent.com/FortOfFans/ToF.github.io/webp/Icon/AvatarFrame/AvatarFrame_114.webp"
	},
	"AvatarFrame_115": {
		"name": "Kafein Pertemanan",
		"icon": "https://raw.githubusercontent.com/FortOfFans/ToF.github.io/webp/Icon/AvatarFrame/AvatarFrame_115.webp"
	},
	"AvatarFrame_116": {
		"name": "Ritme Berkelip",
		"icon": "https://raw.githubusercontent.com/FortOfFans/ToF.github.io/webp/Icon/AvatarFrame/AvatarFrame_116.webp"
	},
	"AvatarFrame_117": {
		"name": "Kilatan Perak",
		"icon": "https://raw.githubusercontent.com/FortOfFans/ToF.github.io/webp/Icon/AvatarFrame/AvatarFrame_117.webp"
	},
	"AvatarFrame_118": {
		"name": "Enchantress Nan Indah",
		"icon": "https://raw.githubusercontent.com/FortOfFans/ToF.github.io/webp/Icon/AvatarFrame/AvatarFrame_118.webp"
	},
	"AvatarFrame_119": {
		"name": "Ular-Kura",
		"icon": "https://raw.githubusercontent.com/FortOfFans/ToF.github.io/webp/Icon/AvatarFrame/AvatarFrame_119.webp"
	},
	"AvatarFrame_120": {
		"name": "Oasis",
		"icon": "https://raw.githubusercontent.com/FortOfFans/ToF.github.io/webp/Icon/AvatarFrame/AvatarFrame_120.webp"
	},
	"AvatarFrame_121": {
		"name": "Agen Elit",
		"icon": "https://raw.githubusercontent.com/FortOfFans/ToF.github.io/webp/Icon/AvatarFrame/AvatarFrame_121.webp"
	},
	"AvatarFrame_122": {
		"name": "Deklarasi Fantasi",
		"icon": "https://raw.githubusercontent.com/FortOfFans/ToF.github.io/webp/Icon/AvatarFrame/AvatarFrame_122.webp"
	},
	"AvatarFrame_123": {
		"name": "Penciptaan Dunia Fantasy P",
		"icon": "https://raw.githubusercontent.com/FortOfFans/ToF.github.io/webp/Icon/AvatarFrame/AvatarFrame_123.webp"
	},
	"AvatarFrame_124": {
		"name": "Penciptaan Dunia Fantasy V",
		"icon": "https://raw.githubusercontent.com/FortOfFans/ToF.github.io/webp/Icon/AvatarFrame/AvatarFrame_124.webp"
	},
	"AvatarFrame_125": {
		"name": "Penciptaan Dunia Fantasy W",
		"icon": "https://raw.githubusercontent.com/FortOfFans/ToF.github.io/webp/Icon/AvatarFrame/AvatarFrame_125.webp"
	},
	"AvatarFrame_126": {
		"name": "Sisik Terbalik",
		"icon": "https://raw.githubusercontent.com/FortOfFans/ToF.github.io/webp/Icon/AvatarFrame/AvatarFrame_126.webp"
	},
	"AvatarFrame_127": {
		"icon": "https://raw.githubusercontent.com/FortOfFans/ToF.github.io/webp/Icon/AvatarFrame/AvatarFrame_127.webp"
	},
	"AvatarFrame_txcreatos_06": {
		"name": "Lautan Lentera",
		"icon": "https://raw.githubusercontent.com/FortOfFans/ToF.github.io/webpOverSea/Icon/AvatarFrame/AvatarFrame_txcreatos_06.webp"
	},
	"AvatarFrame_txshikuang_01": {
		"name": "Pass Pertama Eksekutor Terpercaya v3.2",
		"icon": "https://raw.githubusercontent.com/FortOfFans/ToF.github.io/webpOverSea/Icon/AvatarFrame/AvatarFrame_txshikuang_01.webp"
	},
	"AvatarFrame_koreaMoonFestival_01": {
		"name": "DNT",
		"icon": "https://raw.githubusercontent.com/FortOfFans/ToF.github.io/webpOverSea/Icon/AvatarFrame/AvatarFrame_koreaMoonFestival_01.webp"
	},
	"AvatarFrame_PlayStation33_os01": {
		"name": "Panen Sihir",
		"icon": "https://raw.githubusercontent.com/FortOfFans/ToF.github.io/webpOverSea/Icon/AvatarFrame/AvatarFrame_PlayStation33_os01.webp"
	},
	"AvatarFrame_PlayStation33_os02": {
		"name": "Pelindung Aida",
		"icon": "https://raw.githubusercontent.com/FortOfFans/ToF.github.io/webpOverSea/Icon/AvatarFrame/AvatarFrame_PlayStation33_os02.webp"
	},
	"AvatarFrame_txcreatos_07": {
		"name": "Hutan Azure",
		"icon": "https://raw.githubusercontent.com/FortOfFans/ToF.github.io/webpOverSea/Icon/AvatarFrame/AvatarFrame_txcreatos_07.webp"
	},
	"AvatarFrame_Koreatongyong33_01": {
		"name": "Cincin Api",
		"icon": "https://raw.githubusercontent.com/FortOfFans/ToF.github.io/webpOverSea/Icon/AvatarFrame/AvatarFrame_Koreatongyong33_01.webp"
	},
	"AvatarFrame_tencent_03": {
		"name": "Bilah Serdak Es",
		"icon": "https://raw.githubusercontent.com/FortOfFans/ToF.github.io/webpOverSea/Icon/AvatarFrame/AvatarFrame_tencent_03.webp"
	},
	"AvatarFrame_tencent_04": {
		"name": "Perintis Aida 3",
		"icon": "https://raw.githubusercontent.com/FortOfFans/ToF.github.io/webpOverSea/Icon/AvatarFrame/AvatarFrame_tencent_04.webp"
	},
	"AvatarFrame_tencent_05": {
		"name": "Semangat Jumat",
		"icon": "https://raw.githubusercontent.com/FortOfFans/ToF.github.io/webpOverSea/Icon/AvatarFrame/AvatarFrame_tencent_05.webp"
	},
	"AvatarFrame_PlayStation_02": {
		"name": "Malam",
		"icon": "https://raw.githubusercontent.com/FortOfFans/ToF.github.io/webpOverSea/Icon/AvatarFrame/AvatarFrame_koreaMoonFestival_01.webp"
	},
	"AvatarFrame_Overseas_10": {
		"name": "Broken Dream",
		"icon": "https://raw.githubusercontent.com/FortOfFans/ToF.github.io/webp/Icon/AvatarFrame/AvatarFrame_Overseas_10.webp"
	},
	"AvatarFrame_Overseas_11": {
		"name": "Pass Pertama Eksekutor Terpercaya v3.5",
		"icon": "https://raw.githubusercontent.com/FortOfFans/ToF.github.io/webp/Icon/AvatarFrame/AvatarFrame_Overseas_11.webp"
	},
	"AvatarFrame_Overseas_12": {
		"name": "Fluffy Me",
		"icon": "https://raw.githubusercontent.com/FortOfFans/ToF.github.io/webp/Icon/AvatarFrame/AvatarFrame_Overseas_12.webp"
	},
	"AvatarFrame_Overseas_13": {
		"name": "Perintis Aida 4",
		"icon": "https://raw.githubusercontent.com/FortOfFans/ToF.github.io/webp/Icon/AvatarFrame/AvatarFrame_Overseas_13.webp"
	},
	"AvatarFrame_Overseas_14": {
		"name": "Gelombang Ilusi",
		"icon": "https://raw.githubusercontent.com/FortOfFans/ToF.github.io/webp/Icon/AvatarFrame/AvatarFrame_Overseas_14.webp"
	}
}